<?xml version="1.0" encoding="UTF-8"?> 
<!DOCTYPE sqlMapConfig
	PUBLIC "-//ibatis.apache.org//DTD SQL Map Config 2.0 //EN"
	"http://ibatis.apache.org/dtd/sql-map-config-2.dtd">
<sqlMapConfig>
	<transactionManager type="JDBC">
  		<dataSource type="SIMPLE">
   			<property name="JDBC.Driver" value="oracle.jdbc.driver.OracleDriver" />
   			<property name="JDBC.ConnectionURL" value="jdbc:oracle:thin:@localhost:1521:xe" />
   			<property name="JDBC.Username" value="semi" />
   			<property name="JDBC.Password" value="zxcv1234" />
  		</dataSource>  
 	</transactionManager>
 	
 	
 	<sqlMap resource="kr/co/team2/mappers/admin-item.xml"/>
 	<sqlMap resource="kr/co/team2/mappers/admin-order.xml"/>
 	<sqlMap resource="kr/co/team2/mappers/admin-user.xml"/>
 	<sqlMap resource="kr/co/team2/mappers/search.xml"/>
 	<sqlMap resource="kr/co/team2/mappers/review.xml"/>
 	<sqlMap resource="kr/co/team2/mappers/item.xml" />
 	<sqlMap resource="kr/co/team2/mappers/users.xml"/>
 	<sqlMap resource="kr/co/team2/mappers/item-question.xml"/>
 	<sqlMap resource="kr/co/team2/mappers/my-board.xml"/>
 	<sqlMap resource="kr/co/team2/mappers/cart.xml"/>
 	<sqlMap resource="kr/co/team2/mappers/keyword-Search.xml"/>
 	<sqlMap resource="kr/co/team2/mappers/orders.xml"/>
 	<sqlMap resource="kr/co/team2/mappers/order-list.xml"/>
</sqlMapConfig>